grami/__init__.py
grami/agent.py
grami/agents/__init__.py
grami/agents/async_agent.py
grami/agents/base.py
grami/communication/__init__.py
grami/communication/event_bus.py
grami/communication/websocket.py
grami/core/base.py
grami/memory/README.md
grami/memory/__init__.py
grami/memory/base.py
grami/memory/lru.py
grami/memory/redis_memory.py
grami/providers/__init__.py
grami/providers/fallback_provider.py
grami/providers/gemini_provider.py
grami/providers/openai_provider.py
grami/tools/__init__.py
grami/tools/base.py
grami_ai-0.4.4.dist-info/METADATA
grami_ai-0.4.4.dist-info/WHEEL
grami_ai-0.4.4.dist-info/entry_points.txt
grami_ai-0.4.4.dist-info/licenses/LICENSE
grami_ai-0.4.4.dist-info/RECORD
