Metadata-Version: 2.3
Name: grami-ai
Version: 0.4.4
Summary: A dynamic and flexible AI agent framework for building intelligent, multi-modal AI agents
Project-URL: Homepage, https://github.com/YAFATEK/grami-ai
Project-URL: Documentation, https://grami-ai.readthedocs.io
Project-URL: Repository, https://github.com/YAFATEK/grami-ai
Project-URL: Issues, https://github.com/YAFATEK/grami-ai/issues
Author-email: YAFATEK Solutions / GRAMI Team <support@yafatek.dev>
Maintainer-email: YAFATEK Solutions <support@yafatek.dev>
License: MIT
Keywords: agent,ai,artificial-intelligence,generative-ai,llm,machine-learning
Classifier: Development Status :: 3 - Alpha
Classifier: Intended Audience :: Developers
Classifier: Intended Audience :: Science/Research
Classifier: License :: OSI Approved :: MIT License
Classifier: Operating System :: OS Independent
Classifier: Programming Language :: Python :: 3
Classifier: Programming Language :: Python :: 3.8
Classifier: Programming Language :: Python :: 3.9
Classifier: Programming Language :: Python :: 3.10
Classifier: Programming Language :: Python :: 3.11
Classifier: Programming Language :: Python :: 3.12
Classifier: Topic :: Scientific/Engineering :: Artificial Intelligence
Classifier: Topic :: Software Development :: Libraries :: Python Modules
Requires-Python: >=3.8
Requires-Dist: anthropic>=0.7.0
Requires-Dist: asyncio>=3.4.3
Requires-Dist: google-generativeai>=0.3.1
Requires-Dist: openai>=1.3.0
Requires-Dist: pydantic>=2.0.0
Requires-Dist: python-dotenv
Requires-Dist: redis>=5.0.1
Requires-Dist: requests>=2.28.0
Provides-Extra: dev
Requires-Dist: black>=23.3.0; extra == 'dev'
Requires-Dist: flake8>=6.0.0; extra == 'dev'
Requires-Dist: isort>=5.12.0; extra == 'dev'
Requires-Dist: mypy>=1.3.0; extra == 'dev'
Requires-Dist: pytest-asyncio>=0.21.1; extra == 'dev'
Requires-Dist: pytest>=7.3.1; extra == 'dev'
Provides-Extra: docs
Requires-Dist: myst-parser>=1.0.0; extra == 'docs'
Requires-Dist: sphinx-rtd-theme>=1.2.0; extra == 'docs'
Requires-Dist: sphinx>=5.3.0; extra == 'docs'
Provides-Extra: redis
Requires-Dist: redis>=5.0.1; extra == 'redis'
